metadata_please/__init__.py
metadata_please/py.typed
metadata_please/sdist.py
metadata_please/source_checkout.py
metadata_please/source_checkout_ast.py
metadata_please/types.py
metadata_please/wheel.py
metadata_please/tests/__init__.py
metadata_please/tests/__main__.py
metadata_please/tests/_tar.py
metadata_please/tests/_zip.py
metadata_please/tests/metadata_contents.py
metadata_please/tests/sdist.py
metadata_please/tests/source_checkout.py
metadata_please/tests/wheel.py
metadata_please-0.2.1.dist-info/LICENSE
metadata_please-0.2.1.dist-info/METADATA
metadata_please-0.2.1.dist-info/WHEEL
metadata_please-0.2.1.dist-info/top_level.txt
metadata_please-0.2.1.dist-info/RECORD
