Metadata-Version: 2.1
Name: metadata-please
Version: 0.2.1
Summary: Simple extractor for python artifact metadata
Home-page: https://github.com/python-packaging/metadata-please/
Author: Tim Hatch
Author-email: tim@timhatch.com
License: MIT
Requires-Python: >=3.7
License-File: LICENSE
Requires-Dist: packaging
Requires-Dist: configparser
Requires-Dist: toml ; python_version < "3.11"
Provides-Extra: dev
Requires-Dist: black ==23.12.1 ; extra == 'dev'
Requires-Dist: checkdeps ==0.9.0 ; extra == 'dev'
Requires-Dist: flake8 ==7.0.0 ; extra == 'dev'
Requires-Dist: mypy ==1.8.0 ; extra == 'dev'
Requires-Dist: tox ==4.12.1 ; extra == 'dev'
Requires-Dist: twine ==4.0.2 ; extra == 'dev'
Requires-Dist: ufmt ==2.3.0 ; extra == 'dev'
Requires-Dist: usort ==1.0.7 ; extra == 'dev'
Requires-Dist: wheel ==0.42.0 ; extra == 'dev'
Provides-Extra: test
Requires-Dist: coverage >=6 ; extra == 'test'
